MANIFEST.in
README
setup.cfg
setup.py
apocell.egg-info/PKG-INFO
apocell.egg-info/SOURCES.txt
apocell.egg-info/dependency_links.txt
apocell.egg-info/top_level.txt
apocell_project/apocell.py
apocell_project/bottle.py