Metadata-Version: 1.0
Name: apocell
Version: 1.0.1
Summary: Post-processing for apobec collocation data from cellprofiler
Home-page: www.pei.de
Author: Jan-Hendrik Trösemeier, Sabine Klawitter, Gerald Schumann
Author-email: jan-hendrik.troesemeier@pei.de
License: UNKNOWN
Platform: UNKNOWN
Classifier: Topic :: Utilities
Classifier: License :: OSI Approved :: GNU General Public License v3 or later (GPLv3+)
